[
  {
    "inputs": [
      {
        "internalType": "address payable",
        "name": "_supervisor",
        "type": "address"
      }
    ],
    "stateMutability": "nonpayable",
    "type": "constructor"
  },
  {
    "anonymous": false,
    "inputs": [
      {
        "indexed": false,
        "internalType": "contract Bounty",
        "name": "bounty",
        "type": "address"
      }
    ],
    "name": "BountyCreated",
    "type": "event"
  },
  {
    "inputs": [
      {
        "internalType": "address",
        "name": "",
        "type": "address"
      }
    ],
    "name": "allBounties",
    "outputs": [
      {
        "internalType": "contract Bounty",
        "name": "",
        "type": "address"
      }
    ],
    "stateMutability": "view",
    "type": "function"
  },
  {
    "inputs": [
      {
        "internalType": "uint256",
        "name": "_expiryTimestamp",
        "type": "uint256"
      }
    ],
    "name": "createBounty",
    "outputs": [
      {
        "internalType": "address",
        "name": "",
        "type": "address"
      }
    ],
    "stateMutability": "payable",
    "type": "function"
  },
  {
    "inputs": [],
    "name": "getTotalBounties",
    "outputs": [
      {
        "internalType": "uint256",
        "name": "",
        "type": "uint256"
      }
    ],
    "stateMutability": "pure",
    "type": "function"
  }
]
